cdk_cloudfront_geo_locator/__init__.py
cdk_cloudfront_geo_locator/py.typed
cdk_cloudfront_geo_locator/_jsii/__init__.py
cdk_cloudfront_geo_locator/_jsii/cdk-cloudfront-geo-locator@1.0.0.jsii.tgz
cdk_cloudfront_geo_locator-1.0.0.dist-info/LICENSE
cdk_cloudfront_geo_locator-1.0.0.dist-info/METADATA
cdk_cloudfront_geo_locator-1.0.0.dist-info/WHEEL
cdk_cloudfront_geo_locator-1.0.0.dist-info/top_level.txt
cdk_cloudfront_geo_locator-1.0.0.dist-info/RECORD
