Metadata-Version: 2.1
Name: cdk-cloudfront-geo-locator
Version: 1.0.0
Summary: An AWS CDK construct to create a CloudFront-powered HTTP endpoint delivering requestor's geolocation details.
Home-page: https://github.com/ilkrklc/cdk-cloudfront-geo-locator
Author: Ilker Kilic<ilkrklc@gmail.com>
License: MIT
Project-URL: Source, https://github.com/ilkrklc/cdk-cloudfront-geo-locator
Platform: UNKNOWN
Classifier: Intended Audience :: Developers
Classifier: Operating System :: OS Independent
Classifier: Programming Language :: JavaScript
Classifier: Programming Language :: Python :: 3 :: Only
Classifier: Programming Language :: Python :: 3.8
Classifier: Programming Language :: Python :: 3.9
Classifier: Programming Language :: Python :: 3.10
Classifier: Programming Language :: Python :: 3.11
Classifier: Typing :: Typed
Classifier: Development Status :: 5 - Production/Stable
Classifier: License :: OSI Approved
Requires-Python: ~=3.8
License-File: LICENSE
Requires-Dist: aws-cdk-lib (==2.117.0)
Requires-Dist: constructs (<11.0.0,>=10.0.0)
Requires-Dist: jsii (<2.0.0,>=1.93.0)
Requires-Dist: publication (>=0.0.3)
Requires-Dist: typeguard (~=2.13.3)
